veins_gym/__init__.py
veins_gym/veinsgym_pb2.py
veins_gym-0.3.3.data/data/protobuf/veinsgym.proto
veins_gym-0.3.3.dist-info/LICENSE.txt
veins_gym-0.3.3.dist-info/METADATA
veins_gym-0.3.3.dist-info/WHEEL
veins_gym-0.3.3.dist-info/top_level.txt
veins_gym-0.3.3.dist-info/RECORD
