Metadata-Version: 2.1
Name: veins-gym
Version: 0.3.3
Summary: Reinforcement Learning-based VANET simulations
Home-page: https://www2.tkn.tu-berlin.de/software/veins-gym/
Author: Dominik S. Buse
Author-email: buse@ccs-labs.org
License: UNKNOWN
Platform: UNKNOWN
Classifier: Programming Language :: Python :: 3
Classifier: License :: OSI Approved :: GNU General Public License v2 or later (GPLv2+)
Classifier: Operating System :: OS Independent
Requires-Python: >=3.6
Requires-Dist: gym
Requires-Dist: protobuf
Requires-Dist: zmq
